evalhyd/__init__.py
evalhyd/_evalhyd.cpython-311-darwin.so
evalhyd/evald.py
evalhyd/evalp.py
evalhyd/version.py
evalhyd_python-0.1.2.0.dist-info/LICENCE.rst
evalhyd_python-0.1.2.0.dist-info/METADATA
evalhyd_python-0.1.2.0.dist-info/WHEEL
evalhyd_python-0.1.2.0.dist-info/top_level.txt
evalhyd_python-0.1.2.0.dist-info/RECORD
